airgradient/__init__.py
airgradient/airgradient.py
airgradient/exceptions.py
airgradient/models.py
airgradient/py.typed
airgradient/util.py
airgradient-0.9.1.dist-info/LICENSE.md
airgradient-0.9.1.dist-info/METADATA
airgradient-0.9.1.dist-info/WHEEL
airgradient-0.9.1.dist-info/RECORD
