Metadata-Version: 2.1
Name: airgradient
Version: 0.9.1
Summary: Asynchronous Python client for AirGradient.
Home-page: https://github.com/airgradienthq/python-airgradient
License: MIT
Keywords: Airgradient,api,async,client
Author: Joost Lekkerkerker
Author-email: joostlek@outlook.com
Maintainer: Joost Lekkerkerker
Maintainer-email: joostlek@outlook.com
Requires-Python: >=3.11,<4.0
Classifier: Development Status :: 5 - Production/Stable
Classifier: Framework :: AsyncIO
Classifier: Intended Audience :: Developers
Classifier: License :: OSI Approved :: MIT License
Classifier: Natural Language :: English
Classifier: Programming Language :: Python :: 3
Classifier: Programming Language :: Python :: 3.11
Classifier: Programming Language :: Python :: 3.12
Classifier: Topic :: Software Development :: Libraries :: Python Modules
Requires-Dist: aiohttp (>=3.0.0)
Requires-Dist: mashumaro (>=3.11,<4.0)
Requires-Dist: orjson (>=3.9.0)
Requires-Dist: yarl (>=1.6.0)
Project-URL: Bug Tracker, https://github.com/airgradienthq/python-airgradient/issues
Project-URL: Changelog, https://github.com/airgradienthq/python-airgradient/releases
Project-URL: Documentation, https://github.com/airgradienthq/python-airgradient
Project-URL: Repository, https://github.com/airgradienthq/python-airgradient
